minirpa/__init__.py
minirpa/debug.py
minirpa/main.py
minirpa/__pycache__/__init__.cpython-37.pyc
minirpa-2021.12.23.dist-info/LICENSE
minirpa-2021.12.23.dist-info/METADATA
minirpa-2021.12.23.dist-info/WHEEL
minirpa-2021.12.23.dist-info/entry_points.txt
minirpa-2021.12.23.dist-info/top_level.txt
minirpa-2021.12.23.dist-info/RECORD
